AUTHORS
MANIFEST.in
README.rst
bbnotify.py
setup.py
bbnotify/__init__.py
bbnotify/daemonize.py
bbnotify/notificator.py
bbnotify.egg-info/PKG-INFO
bbnotify.egg-info/SOURCES.txt
bbnotify.egg-info/dependency_links.txt
bbnotify.egg-info/entry_points.txt
bbnotify.egg-info/not-zip-safe
bbnotify.egg-info/top_level.txt
bbnotify/media/green.png
bbnotify/media/grey.png
bbnotify/media/icons.svg
bbnotify/media/red.png
dist/bbnotify-0.3.tar.gz
setuptools_dummy-0.1.0.4-py2.7.egg/setuptools_dummy.py
setuptools_dummy-0.1.0.4-py2.7.egg/EGG-INFO/PKG-INFO
setuptools_dummy-0.1.0.4-py2.7.egg/EGG-INFO/SOURCES.txt
setuptools_dummy-0.1.0.4-py2.7.egg/EGG-INFO/dependency_links.txt
setuptools_dummy-0.1.0.4-py2.7.egg/EGG-INFO/entry_points.txt
setuptools_dummy-0.1.0.4-py2.7.egg/EGG-INFO/top_level.txt
setuptools_dummy-0.1.0.4-py2.7.egg/EGG-INFO/zip-safe