Metadata-Version: 1.0
Name: bbnotify
Version: 0.3
Summary: Tray notification for BuildBot
Home-page: http://github.com/aleszoulek/bbnotify
Author: Ales Zoulek
Author-email: ales.zoulek@gmail.com
License: BSD
Keywords: buildbot,tray,notification
Platform: any
Classifier: Development Status :: 5 - Production/Stable
Classifier: Environment :: Web Environment
Classifier: Intended Audience :: Developers
Classifier: Natural Language :: English
Classifier: Operating System :: OS Independent
Classifier: Programming Language :: Python
